{ "columns":8,
 "image":"..\/tiles\/palett-town.png",
 "imageheight":1472,
 "imagewidth":128,
 "margin":0,
 "name":"palett-town",
 "spacing":0,
 "tilecount":736,
 "tiledversion":"1.11.0",
 "tileheight":16,
 "tiles":[
        {
         "id":0,
         "properties":[
                {
                 "name":"test",
                 "type":"string",
                 "value":"first-black-tile"
                }]
        }, 
        {
         "id":3,
         "properties":[
                {
                 "name":"solid",
                 "type":"bool",
                 "value":true
                }]
        }, 
        {
         "id":11,
         "properties":[
                {
                 "name":"solid",
                 "type":"bool",
                 "value":true
                }]
        }, 
        {
         "id":12,
         "properties":[
                {
                 "name":"solid",
                 "type":"bool",
                 "value":true
                }]
        }, 
        {
         "id":28,
         "properties":[
                {
                 "name":"solid",
                 "type":"bool",
                 "value":true
                }]
        }, 
        {
         "id":29,
         "properties":[
                {
                 "name":"solid",
                 "type":"bool",
                 "value":true
                }]
        }, 
        {
         "id":30,
         "properties":[
                {
                 "name":"solid",
                 "type":"bool",
                 "value":true
                }]
        }, 
        {
         "id":31,
         "properties":[
                {
                 "name":"solid",
                 "type":"bool",
                 "value":true
                }]
        }, 
        {
         "id":36,
         "properties":[
                {
                 "name":"solid",
                 "type":"bool",
                 "value":true
                }]
        }, 
        {
         "id":37,
         "properties":[
                {
                 "name":"solid",
                 "type":"bool",
                 "value":true
                }]
        }, 
        {
         "id":38,
         "properties":[
                {
                 "name":"solid",
                 "type":"bool",
                 "value":true
                }]
        }, 
        {
         "id":39,
         "properties":[
                {
                 "name":"solid",
                 "type":"bool",
                 "value":true
                }]
        }, 
        {
         "id":44,
         "properties":[
                {
                 "name":"solid",
                 "type":"bool",
                 "value":true
                }]
        }, 
        {
         "id":45,
         "properties":[
                {
                 "name":"solid",
                 "type":"bool",
                 "value":true
                }]
        }, 
        {
         "id":46,
         "properties":[
                {
                 "name":"solid",
                 "type":"bool",
                 "value":true
                }]
        }, 
        {
         "id":47,
         "properties":[
                {
                 "name":"solid",
                 "type":"bool",
                 "value":true
                }]
        }, 
        {
         "id":52,
         "properties":[
                {
                 "name":"solid",
                 "type":"bool",
                 "value":true
                }]
        }, 
        {
         "id":53,
         "properties":[
                {
                 "name":"solid",
                 "type":"bool",
                 "value":true
                }]
        }, 
        {
         "id":54,
         "properties":[
                {
                 "name":"solid",
                 "type":"bool",
                 "value":true
                }]
        }, 
        {
         "id":55,
         "properties":[
                {
                 "name":"solid",
                 "type":"bool",
                 "value":true
                }]
        }, 
        {
         "id":60,
         "properties":[
                {
                 "name":"solid",
                 "type":"bool",
                 "value":true
                }]
        }, 
        {
         "id":61,
         "properties":[
                {
                 "name":"solid",
                 "type":"bool",
                 "value":true
                }]
        }, 
        {
         "id":62,
         "properties":[
                {
                 "name":"solid",
                 "type":"bool",
                 "value":true
                }]
        }, 
        {
         "id":63,
         "properties":[
                {
                 "name":"solid",
                 "type":"bool",
                 "value":true
                }]
        }, 
        {
         "id":104,
         "properties":[
                {
                 "name":"solid",
                 "type":"bool",
                 "value":true
                }]
        }, 
        {
         "id":105,
         "properties":[
                {
                 "name":"solid",
                 "type":"bool",
                 "value":true
                }]
        }, 
        {
         "id":106,
         "properties":[
                {
                 "name":"solid",
                 "type":"bool",
                 "value":true
                }]
        }, 
        {
         "id":112,
         "properties":[
                {
                 "name":"solid",
                 "type":"bool",
                 "value":true
                }]
        }, 
        {
         "id":113,
         "properties":[
                {
                 "name":"solid",
                 "type":"bool",
                 "value":true
                }]
        }, 
        {
         "id":114,
         "properties":[
                {
                 "name":"solid",
                 "type":"bool",
                 "value":true
                }]
        }, 
        {
         "id":120,
         "properties":[
                {
                 "name":"solid",
                 "type":"bool",
                 "value":true
                }]
        }, 
        {
         "id":121,
         "properties":[
                {
                 "name":"solid",
                 "type":"bool",
                 "value":true
                }]
        }, 
        {
         "id":122,
         "properties":[
                {
                 "name":"solid",
                 "type":"bool",
                 "value":true
                }]
        }, 
        {
         "id":159,
         "properties":[
                {
                 "name":"solid",
                 "type":"bool",
                 "value":true
                }]
        }, 
        {
         "id":167,
         "properties":[
                {
                 "name":"solid",
                 "type":"bool",
                 "value":true
                }]
        }, 
        {
         "id":169,
         "properties":[
                {
                 "name":"solid",
                 "type":"bool",
                 "value":false
                }, 
                {
                 "name":"test",
                 "type":"string",
                 "value":"door"
                }]
        }, 
        {
         "id":175,
         "properties":[
                {
                 "name":"solid",
                 "type":"bool",
                 "value":true
                }]
        }, 
        {
         "id":183,
         "properties":[
                {
                 "name":"solid",
                 "type":"bool",
                 "value":true
                }]
        }],
 "tilewidth":16,
 "type":"tileset",
 "version":"1.10"
}